.installed.cfg
.mr.developer.cfg
.travis.yml
MANIFEST.in
README.rst
bootstrap.py
buildout.cfg
pre-commit-check.sh
setup.cfg
setup.py
buildout.d/base.cfg
buildout.d/development.cfg
buildout.d/travis.cfg
buildout.d/versions.cfg
docs/HISTORY.rst
docs/LICENSE.rst
docs/images/cart_actions.png
docs/images/document_byline.png
docs/images/portal_actions.png
src/slc/__init__.py
src/slc/__init__.pyc
src/slc.cart.egg-info/PKG-INFO
src/slc.cart.egg-info/SOURCES.txt
src/slc.cart.egg-info/dependency_links.txt
src/slc.cart.egg-info/entry_points.txt
src/slc.cart.egg-info/namespace_packages.txt
src/slc.cart.egg-info/not-zip-safe
src/slc.cart.egg-info/requires.txt
src/slc.cart.egg-info/top_level.txt
src/slc/cart/__init__.py
src/slc/cart/__init__.pyc
src/slc/cart/config.py
src/slc/cart/config.pyc
src/slc/cart/configure.zcml
src/slc/cart/interfaces.py
src/slc/cart/interfaces.pyc
src/slc/cart/actions/__init__.py
src/slc/cart/actions/__init__.pyc
src/slc/cart/actions/copy.py
src/slc/cart/actions/copy.pyc
src/slc/cart/actions/cut.py
src/slc/cart/actions/cut.pyc
src/slc/cart/actions/delete.py
src/slc/cart/actions/delete.pyc
src/slc/cart/actions/download.py
src/slc/cart/actions/download.pyc
src/slc/cart/browser/.DS_Store
src/slc/cart/browser/__init__.py
src/slc/cart/browser/__init__.pyc
src/slc/cart/browser/cart.py
src/slc/cart/browser/cart.pyc
src/slc/cart/browser/configure.zcml
src/slc/cart/browser/overrides/.gitignore
src/slc/cart/browser/overrides/plone.app.layout.viewlets.document_byline.pt
src/slc/cart/browser/static/.DS_Store
src/slc/cart/browser/static/.gitignore
src/slc/cart/browser/static/cart.css
src/slc/cart/browser/static/cart.js
src/slc/cart/browser/templates/cart.pt
src/slc/cart/profiles/default/actions.xml
src/slc/cart/profiles/default/browserlayer.xml
src/slc/cart/profiles/default/cssregistry.xml
src/slc/cart/profiles/default/jsregistry.xml
src/slc/cart/profiles/default/metadata.xml
src/slc/cart/profiles/default/registry.xml
src/slc/cart/profiles/default/rolemap.xml
src/slc/cart/tests/__init__.py
src/slc/cart/tests/__init__.pyc
src/slc/cart/tests/base.py
src/slc/cart/tests/base.pyc
src/slc/cart/tests/test_actions.py
src/slc/cart/tests/test_actions.pyc
src/slc/cart/tests/test_cart.py
src/slc/cart/tests/test_cart.pyc
src/slc/cart/tests/test_setup.py
