Metadata-Version: 1.0
Name: slc.cart
Version: 1.1
Summary: Cart-like end-user support for batching.
Home-page: https://github.com/syslabcom/slc.cart
Author: syslab.com
Author-email: UNKNOWN
License: BSD
Keywords: Plone Python
Platform: UNKNOWN
Classifier: Framework :: Plone
Classifier: Programming Language :: Python
